z2/__init__.py
z2/__main__.py
z2/network/__init__.py
z2/network/__main__.py
z2/process/__init__.py
z2/process/__main__.py
z2/process/control.py
z2/strings/__init__.py
z2/strings/__main__.py
z2/strings/control.py
z2/utils/__init__.py
z2/utils/infra.py
z2-0.0.30.dist-info/LICENSE.md
z2-0.0.30.dist-info/WHEEL
z2-0.0.30.dist-info/METADATA
z2-0.0.30.dist-info/RECORD
