Metadata-Version: 2.1
Name: z2
Version: 0.0.30
Summary: A set of tools
Home-page: https://github.com/mpenning/z2/
License: BSD-3-Clause
Keywords: tool
Author: Mike Pennington
Author-email: mike@pennington.net
Requires-Python: >=3.6
Classifier: Development Status :: 5 - Production/Stable
Classifier: Environment :: Plugins
Classifier: Intended Audience :: Developers
Classifier: Intended Audience :: System Administrators
Classifier: License :: OSI Approved :: BSD License
Classifier: Operating System :: OS Independent
Classifier: Programming Language :: Python
Classifier: Programming Language :: Python :: 3
Classifier: Programming Language :: Python :: 3.10
Classifier: Programming Language :: Python :: 3.6
Classifier: Programming Language :: Python :: 3.7
Classifier: Programming Language :: Python :: 3.8
Classifier: Programming Language :: Python :: 3.9
Classifier: Topic :: Software Development :: Libraries :: Python Modules
Requires-Dist: ciscoconfparse (>=1.6.0)
Requires-Dist: loguru (==0.6.0)
Requires-Dist: sh (>=1.14)
Requires-Dist: toml (==0.10.2)
Project-URL: Documentation, http://www.pennington.net/py/z2/
